watermark.py
watermark.py-0.0.3.post3.dist-info/LICENSE
watermark.py-0.0.3.post3.dist-info/WHEEL
watermark.py-0.0.3.post3.dist-info/METADATA
watermark.py-0.0.3.post3.dist-info/RECORD
